ccrypto/__init__.py
ccrypto/cmc.py
ccrypto/get_cmc_coins_by_mcap.py
ccrypto/mycryptokeys.py
ccrypto-0.0.14.dist-info/LICENCE
ccrypto-0.0.14.dist-info/METADATA
ccrypto-0.0.14.dist-info/WHEEL
ccrypto-0.0.14.dist-info/top_level.txt
ccrypto-0.0.14.dist-info/RECORD
