Metadata-Version: 2.1
Name: ccrypto
Version: 0.0.14
Summary: Crypto-Finance Python library for crypto markets and data analysis by QuantAtRisk.com
Home-page: https://github.com/quantatrisk/ccrypto
Author: Pawel Lachowicz
Author-email: pawel.lachowicz@quantatrisk.com
License: MIT
License-File: LICENCE
Requires-Dist: numpy
Requires-Dist: pandas
Requires-Dist: python-binance (==1.0.17)
Requires-Dist: matplotlib
Requires-Dist: requests
